{
  "project_info": {
    "project_number": "566860187383",
    "firebase_url": "https://my-app-5c471.firebaseio.com",
    "project_id": "my-app-5c471",
    "storage_bucket": "my-app-5c471.appspot.com"
  },
  "client": [
    {
      "client_info": {
        "mobilesdk_app_id": "1:566860187383:android:1c46d13e28751cd2",
        "android_client_info": {
          "package_name": "com.politicoapp"
        }
      },
      "oauth_client": [
        {
          "client_id": "566860187383-na25epfur2dgjqgns1cnu9m8ekihlb05.apps.googleusercontent.com",
          "client_type": 1,
          "android_info": {
            "package_name": "com.politicoapp",
            "certificate_hash": "f7f791da847da68f24224b5933f1634eb991e2de"
          }
        },
        {
          "client_id": "566860187383-qqpeagojv54elphusr13tir84nbt0je5.apps.googleusercontent.com",
          "client_type": 1,
          "android_info": {
            "package_name": "com.politicoapp",
            "certificate_hash": "143c882fe1d7e54e031316dba3cfe2e486e602ca"
          }
        },
        {
          "client_id": "566860187383-ant0bjv496hmgdmj3t2hhk9qlqnh5e70.apps.googleusercontent.com",
          "client_type": 3
        }
      ],
      "api_key": [
        {
          "current_key": "AIzaSyCtNPYhG7ED7q96lIlWy7KIQNqKpo3jCT0"
        }
      ],
      "services": {
        "analytics_service": {
          "status": 1
        },
        "appinvite_service": {
          "status": 2,
          "other_platform_oauth_client": [
            {
              "client_id": "566860187383-ant0bjv496hmgdmj3t2hhk9qlqnh5e70.apps.googleusercontent.com",
              "client_type": 3
            }
          ]
        },
        "ads_service": {
          "status": 2
        }
      }
    }
  ],
  "configuration_version": "1"
}